{
  "abstract": null,
  "authors": [
    {
      "name": "Maximilian Wendlinger"
    },
    {
      "name": "Kilian Tscharke"
    },
    {
      "name": "Pascal Debus"
    }
  ],
  "citation": {
    "$path": "citation.txt"
  },
  "changelog": [
    "version 0.1 : initial public release"
  ],
  "license": "[CC BY-SA 4.0](https://creativecommons.org/licenses/by-sa/4.0/deed.en)",
  "sourceCodeUrl": null,
  "tags": [
    "Other"
  ],
  "title": "Plus Minus",
  "description": "This dataset contains labeled 16x16-pixel grayscale images of minus signs, plus signs, and right/left half-plus signs.",
  "usingThisDataset": {
    "$path": "using_this_dataset.md"
  },
  "heroImage": "https://assets.cloud.pennylane.ai/datasets/generic/hero/Datasets_GenericHero_2.png",
  "thumbnail": "Dataset_AdversarialRobustness_Thumb.png",
  "extra": {},
  "dateOfLastModification": "2024-09-16",
  "dateOfPublication": "2024-09-16"
}
